{
  "exportKind": "branch-scenario",
  "branch": "onConnect",
  "branchLabel": "On connect",
  "scenarioTitle": "UserCase Beta: Measured modular UserCase: onConnect → GetJournal → journal1",
  "deviceKind": "microphone",
  "subgraph": {
    "entry": "on-connect-event",
    "nodes": [
      {
        "id": "on-connect-event",
        "blockKind": "custom",
        "position": {
          "x": -144,
          "y": -96
        },
        "label": "On connect",
        "nodeKind": "event",
        "system": true,
        "eventVariant": "handler"
      },
      {
        "id": "node-is-valid-mqm97w5v-17",
        "blockKind": "custom",
        "position": {
          "x": 320,
          "y": -96
        },
        "label": "isValid",
        "nodeKind": "is-valid"
      },
      {
        "id": "node-get-journal-mqm98hvn-18",
        "blockKind": "custom",
        "position": {
          "x": 456,
          "y": 16
        },
        "label": "GetJournal",
        "nodeKind": "get-journal"
      },
      {
        "id": "node-variable-set-var-JournalRef-mqm9dl4a-6-mqm9du8z-8",
        "blockKind": "custom",
        "position": {
          "x": 784,
          "y": -96
        },
        "label": "journal1",
        "nodeKind": "variable-set",
        "variableId": "var-JournalRef-mqm9dl4a-6"
      }
    ],
    "edges": [
      {
        "source": "on-connect-event",
        "sourceHandle": "exec-out",
        "target": "node-is-valid-mqm97w5v-17",
        "targetHandle": "exec-in",
        "kind": "exec"
      },
      {
        "source": "on-connect-event",
        "sourceHandle": "server",
        "target": "node-is-valid-mqm97w5v-17",
        "targetHandle": "value",
        "kind": "data",
        "dataType": "ServerRef"
      },
      {
        "source": "on-connect-event",
        "sourceHandle": "server",
        "target": "node-get-journal-mqm98hvn-18",
        "targetHandle": "server",
        "kind": "data",
        "dataType": "ServerRef"
      },
      {
        "source": "node-is-valid-mqm97w5v-17",
        "sourceHandle": "exec-true-out",
        "target": "node-variable-set-var-JournalRef-mqm9dl4a-6-mqm9du8z-8",
        "targetHandle": "exec-in",
        "kind": "exec"
      },
      {
        "source": "node-get-journal-mqm98hvn-18",
        "sourceHandle": "journal",
        "target": "node-variable-set-var-JournalRef-mqm9dl4a-6-mqm9du8z-8",
        "targetHandle": "value",
        "kind": "data",
        "dataType": "JournalRef"
      }
    ]
  },
  "variables": [
    {
      "id": "var-JournalRef-mqm9dl4a-6",
      "name": "journal1",
      "type": "JournalRef",
      "value": null
    }
  ],
  "referencedVariableIds": [
    "var-JournalRef-mqm9dl4a-6"
  ],
  "exportedAt": "2026-06-21T15:43:05.190Z",
  "userCaseId": "usercase-mvp-microphone-beta",
  "userCaseBranch": "onConnect",
  "referenceVariableSlots": []
}
